{
  "document": {
    "filename": "lambing_storm__unprompted__s4.txt",
    "source": "unknown",
    "type": "unknown",
    "date": "unknown",
    "word_count": 7426,
    "metadata": {}
  },
  "pipeline": {
    "version": "v1.0",
    "schema_version": "1.0.0",
    "timestamp": "2026-06-10T19:44:31.827336",
    "components": [
      "D18++",
      "ai_detection_patterns",
      "emotion_analysis",
      "style_features"
    ]
  },
  "d18_profile": {
    "lexical_density": 0.5071956960322798,
    "content_words": 3771,
    "function_words": 3664,
    "abstract_ratio": 0.6878980891719745,
    "abstract_words": 216,
    "concrete_words": 98,
    "abstract_per_100": 2.9051782111634163,
    "concrete_per_100": 1.3180901143241426,
    "formality_index": 0.021810803956378393,
    "latinate_count": 86,
    "germanic_count": 3857,
    "latinate_per_100": 1.1566913248150639,
    "germanic_per_100": 51.87626092804304,
    "complexity_score": 2.3906882591093117,
    "subordinate_clauses": 30,
    "coordinate_clauses": 1121,
    "avg_clause_length": 30.101214574898787,
    "mean_paragraph_length": 928.25,
    "stdev_paragraph_length": 1509.2415077022724,
    "paragraph_cv": 1.6258998197708294,
    "dominant_field": "perception",
    "field_distribution": {
      "emotion": 0.20454545454545456,
      "action": 0.14772727272727273,
      "perception": 0.25,
      "communication": 0.1590909090909091,
      "social": 0.11363636363636363,
      "cognition": 0.125
    },
    "sentiment_score": 0.003138306451612906,
    "repetition_ratio": 0.927236045729657,
    "repeated_words": 6894,
    "unique_repeated": 386,
    "metaphor_per_100": 0.20174848688634836,
    "metaphor_count": 15,
    "past_ratio": 0.14377510040160643,
    "present_ratio": 0.03132530120481928,
    "future_ratio": 0.8248995983935743,
    "dominant_tense": "future",
    "word_count": 7435,
    "sentence_count": 247,
    "paragraph_count": 8,
    "char_ngram_mean": 0.02639604490029545,
    "char_ngram_std": 0.03544536378176398,
    "char_ngram_nonzero": 512,
    "function_word_ratio_extended": 0.4151983860121049,
    "pronoun_first_sing_ratio": 0.01891891891891892,
    "pronoun_first_plur_ratio": 0.008108108108108109,
    "pronoun_second_ratio": 0.04594594594594595,
    "pronoun_third_ratio": 0.927027027027027,
    "dominant_perspective": "third_person",
    "self_focus_ratio": 0.02702702702702703,
    "sentence_mean_length": 30.101214574898787,
    "sentence_median_length": 7.0,
    "sentence_std_dev": 259.07340705182344,
    "sentence_cv": 8.606742641802338,
    "hedge_count": 3,
    "epistemic_count": 0,
    "hedge_per_100": 0.04034969737726967,
    "epistemic_per_100": 0.0,
    "certainty_index": -1.0,
    "ttr": 0.12468056489576328,
    "unique_types": 927,
    "hapax_legomena": 541,
    "vocabulary_richness": 0.19744451916610625,
    "top_bigrams": [
      "red rimmed",
      "amniotic fluid",
      "north wall",
      "bellies low",
      "another night",
      "delivery boot",
      "delivery sleeve",
      "spring grass",
      "have time",
      "same ache",
      "kerosene lamps",
      "sharp as",
      "man who",
      "already moving",
      "feel relief"
    ],
    "top_trigrams": [
      "eyes red rimmed",
      "carry without complaint",
      "their bellies low",
      "ewes kept coming",
      "did have time",
      "did feel relief",
      "mama eli said"
    ],
    "exclamation_per_1k": 0.0,
    "question_per_1k": 0.40349697377269667,
    "em_dash_per_1k": 0.0,
    "ellipsis_per_1k": 0.0,
    "semicolon_per_1k": 0.0
  },
  "ai_detection": {
    "not_x_but_y_score": 0,
    "em_dash_score": 0,
    "uniformity_score": 0,
    "beat_inconsistency_score": 100,
    "not_x_but_y_count": 0,
    "not_x_but_y_rate": 0.0,
    "em_dash_count": 0,
    "em_dash_rate": 0.0,
    "sentence_opening_entropy": 7.232523741891507,
    "paragraph_variance_cv": 1.4493396549015818,
    "word_count": 7426
  },
  "emotion": {
    "vader": {
      "compound": 0.003138306451612906,
      "positive": 0.07299193548387098,
      "negative": 0.05006451612903227,
      "neutral": 0.8769435483870963,
      "compound_mean": 0.003138306451612906,
      "compound_median": 0.0,
      "compound_std": 0.2813508128000716,
      "compound_min": -0.7096,
      "compound_max": 0.7579,
      "compound_q25": 0.0,
      "compound_q75": 0.0,
      "word_count": 7426,
      "sentence_count": 248
    },
    "goemotions": null
  },
  "style_features": {
    "token_count": 7435,
    "sentence_count": 247,
    "paragraph_count": 8,
    "unique_types": 927.0,
    "hapax_legomena": 541.0,
    "avg_word_length": 3.9463349024882315,
    "em_dash_per_1k": 0.0,
    "en_dash_per_1k": 0.0,
    "double_hyphen_per_1k": 0.0,
    "em_dash_total": 0.0,
    "em_dash_combined_per_1k": 0.0,
    "em_dash_reducible_count": 0.0,
    "em_dash_reducible_pct": 0.0,
    "em_dash_interruption": 0.0,
    "em_dash_apposition": 0.0,
    "em_dash_amplification": 0.0,
    "em_dash_parenthetical": 0.0,
    "em_dash_glue": 0.0,
    "ellipsis_glyph_per_1k": 0.0,
    "ellipsis_triple_per_1k": 0.0,
    "semicolon_per_1k": 0.0,
    "colon_per_1k": 0.13449899125756556,
    "parentheses_per_1k": 0.0,
    "bracket_per_1k": 0.0,
    "exclamation_per_1k": 0.0,
    "question_per_1k": 0.40349697377269667,
    "interrobang_per_1k": 0.0,
    "caps_word_ratio": 0.0,
    "dialogue_line_ratio": 0.0,
    "dialogue_line_count": 0.0,
    "dash_led_dialogue_ratio": 0.0,
    "avg_words_between_dialogue": 0.0,
    "speaker_tag_rate_per_1k": 1.6139878950907867,
    "hedge_per_1k": 0.40349697377269667,
    "booster_per_1k": 0.8069939475453933,
    "modal_per_1k": 4.034969737726968,
    "modal_must_ratio": 0.0,
    "modal_should_ratio": 0.03333333333333333,
    "modal_can_ratio": 0.1,
    "modal_could_ratio": 0.03333333333333333,
    "modal_might_ratio": 0.06666666666666667,
    "modal_would_ratio": 0.7666666666666667,
    "not_x_but_y_per_1k": 0.13449899125756556,
    "simile_like_per_1k": 0.40349697377269667,
    "simile_as_if_per_1k": 0.40349697377269667,
    "polysyndeton_and_per_1k": 10.759919300605246,
    "discourse_marker_per_sent": 0.0,
    "sentence_mean_length": 30.101214574898787,
    "sentence_median_length": 7,
    "sentence_std_dev": 259.07340705182344,
    "sentence_long_share": 0.048582995951417005,
    "sentence_p90_length": 27.400000000000006,
    "sentence_length_entropy": 2.7959068454331684,
    "paragraph_length_entropy": 2.5,
    "paragraph_mean_length": 929.375,
    "paragraph_std_dev": 1412.1148977243317,
    "paragraph_cv": 1.519424234269624,
    "sentences_per_para_mean": 30.875,
    "sentences_per_para_std": 13.887381862683837,
    "sentences_per_para_cv": 0.4497937445403672,
    "sentences_per_para_entropy": 2.4056390622295662,
    "cconj_per_1k": 13.449899125756557,
    "sconj_per_1k": 5.78345662407532,
    "advcl_per_1k": 10.087424344317418,
    "ccomp_per_1k": 6.05245460659045,
    "mark_per_1k": 4.707464694014795,
    "verbless_sentence_ratio": 0.05668016194331984,
    "participial_opening_ratio": 0.0,
    "fragment_ratio": 0.3805668016194332,
    "short_sentence_ratio": 0.5060728744939271,
    "parenthetical_per_1k": 0.0,
    "ttr": 0.12468056489576328,
    "hapax_ratio": 0.07276395427034298,
    "propn_ratio": 0.009549428379287156,
    "diacritic_ratio": 0.0,
    "caps_word_count": 0.0,
    "noun_per_100": 23.685272360457297,
    "verb_per_100": 7.330195023537324,
    "adj_per_100": 16.933422999327504,
    "adv_per_100": 1.9636852723604572,
    "pron_per_100": 6.079354404841963,
    "sight_per_100": 1.0221923335574983,
    "sound_per_100": 1.1297915265635508,
    "smell_per_100": 0.32279757901815737,
    "taste_per_100": 0.10759919300605246,
    "touch_per_100": 2.2326832548755884,
    "sensory_density_per_100": 4.815063887020847,
    "sensory_dominant": "touch",
    "sensory_dominant_pct": 46.36871508379888,
    "sensory_entropy": 0.8025420042984392,
    "footnote_marker_per_1k": 0.0,
    "italics_token_count": 0.0,
    "smallcaps_token_count": 0.0,
    "translator_flag": 0.0,
    "edition_year": 0.0
  }
}