{
  "document": {
    "filename": "sense-and-sensibility-jane-austen-1811-13917f75.txt",
    "source": "Project Gutenberg eBook #161 (https://www.gutenberg.org/ebooks/161)",
    "type": "unknown",
    "date": "unknown",
    "word_count": 118747,
    "metadata": {
      "title": "Sense and Sensibility",
      "author": "Jane Austen",
      "creator": "Austen, Jane",
      "language": "en",
      "year": "1811",
      "published": "1811",
      "source": "Project Gutenberg eBook #161 (https://www.gutenberg.org/ebooks/161)",
      "rights": "Public domain in the USA (first published 1811)",
      "paragraphs": "1857",
      "word_count": "118747",
      "output_hash": "13917f75"
    },
    "form": "novel",
    "translation_status": "original_english",
    "translator": null,
    "fidelity_verdict": "clean",
    "centroid_membership": {
      "fiction_centroid": true,
      "translator_envelope": false,
      "control_shelf_calibration": true
    },
    "manifest_source_hash": "13917f75",
    "release_eligible_for_aggregates": true,
    "release_eligible_for_quotation": true
  },
  "pipeline": {
    "version": "v1.0",
    "schema_version": "1.0.0",
    "timestamp": "2026-06-10T10:06:45.884344",
    "components": [
      "D18++",
      "ai_detection_patterns",
      "emotion_analysis",
      "style_features"
    ]
  },
  "d18_profile": {
    "lexical_density": 0.4486065277812765,
    "content_words": 53425,
    "function_words": 65666,
    "abstract_ratio": 0.7084262148907713,
    "abstract_words": 1589,
    "concrete_words": 654,
    "abstract_per_100": 1.334273790630694,
    "concrete_per_100": 0.5491598861374916,
    "formality_index": 0.0993542058366713,
    "latinate_count": 6077,
    "germanic_count": 55088,
    "latinate_per_100": 5.102820532198067,
    "germanic_per_100": 46.2570639259054,
    "complexity_score": 1.0237839001291433,
    "subordinate_clauses": 2192,
    "coordinate_clauses": 5129,
    "avg_clause_length": 25.633017649591046,
    "mean_paragraph_length": 63.945611200861606,
    "stdev_paragraph_length": 70.85875454944988,
    "paragraph_cv": 1.1081097391793344,
    "dominant_field": "social",
    "field_distribution": {
      "social": 0.3135240890193201,
      "emotion": 0.12839325018341893,
      "action": 0.06285155294693079,
      "cognition": 0.24406945463438492,
      "perception": 0.1347517730496454,
      "communication": 0.11640988016629983
    },
    "sentiment_score": 0.15074822445561142,
    "repetition_ratio": 0.9796206262437968,
    "repeated_words": 116664,
    "unique_repeated": 3856,
    "metaphor_per_100": 1.115113652584998,
    "metaphor_count": 1328,
    "past_ratio": 0.5898812243033349,
    "present_ratio": 0.32160804020100503,
    "future_ratio": 0.08851073549566012,
    "dominant_tense": "past",
    "word_count": 119091,
    "sentence_count": 4646,
    "paragraph_count": 1857,
    "char_ngram_mean": 0.04131978805915354,
    "char_ngram_std": 0.015678013737289307,
    "char_ngram_nonzero": 512,
    "function_word_ratio_extended": 0.3065722850593244,
    "pronoun_first_sing_ratio": 0.19935426690301342,
    "pronoun_first_plur_ratio": 0.023930108888326158,
    "pronoun_second_ratio": 0.10224107368954166,
    "pronoun_third_ratio": 0.6744745505191188,
    "dominant_perspective": "third_person",
    "self_focus_ratio": 0.22328437579133958,
    "sentence_mean_length": 25.63387860525183,
    "sentence_median_length": 20.0,
    "sentence_std_dev": 20.726288660789024,
    "sentence_cv": 0.8085506286412175,
    "hedge_count": 505,
    "epistemic_count": 307,
    "hedge_per_100": 0.4240454778278795,
    "epistemic_per_100": 0.2577860627587307,
    "certainty_index": -0.2438423645320197,
    "ttr": 0.052757974993912216,
    "unique_types": 6283,
    "hapax_legomena": 2427,
    "vocabulary_richness": 0.07313734875011546,
    "top_bigrams": [
      "bolder rider",
      "colicky gout",
      "dr davies",
      "minuter propensities",
      "pall mall",
      "yew arbour",
      "flannel waistcoat",
      "kensington gardens",
      "east indies",
      "grecian temple",
      "hanover square",
      "mulberry tree",
      "t\u00eate \u00e0",
      "\u00e0 t\u00eate",
      "piano forte"
    ],
    "top_trigrams": [
      "t\u00eate \u00e0 t\u00eate",
      "two penny post",
      "mr gray shop",
      "match takes place",
      "bolder rider in",
      "a bolder rider",
      "so obligingly bestowed"
    ],
    "exclamation_per_1k": 4.693889546649201,
    "question_per_1k": 3.803813890218404,
    "em_dash_per_1k": 7.263353234081501,
    "ellipsis_per_1k": 0.025190820465022547,
    "semicolon_per_1k": 13.267165444911873
  },
  "ai_detection": {
    "not_x_but_y_score": 0,
    "em_dash_score": 22.843945531255528,
    "uniformity_score": 0,
    "beat_inconsistency_score": 100,
    "not_x_but_y_count": 0,
    "not_x_but_y_rate": 0.0,
    "em_dash_count": 865,
    "em_dash_rate": 7.284394553125553,
    "sentence_opening_entropy": 10.876567499788269,
    "paragraph_variance_cv": 0.8401457207887607,
    "word_count": 118747
  },
  "emotion": {
    "vader": {
      "compound": 0.15074822445561142,
      "positive": 0.11364003350083758,
      "negative": 0.06498241206030148,
      "neutral": 0.8213752093802321,
      "compound_mean": 0.15074822445561142,
      "compound_median": 0.0,
      "compound_std": 0.4341864525781235,
      "compound_min": -0.9604,
      "compound_max": 0.9851,
      "compound_q25": 0.0,
      "compound_q75": 0.4939,
      "word_count": 118747,
      "sentence_count": 5970
    },
    "goemotions": null
  },
  "style_features": {
    "token_count": 119091,
    "sentence_count": 4645,
    "paragraph_count": 10531,
    "unique_types": 6283.0,
    "hapax_legomena": 2427.0,
    "avg_word_length": 4.369188267795216,
    "em_dash_per_1k": 7.263353234081501,
    "en_dash_per_1k": 0.0,
    "double_hyphen_per_1k": 0.0,
    "em_dash_total": 865.0,
    "em_dash_combined_per_1k": 7.263353234081501,
    "em_dash_reducible_count": 773.0,
    "em_dash_reducible_pct": 89.36416184971098,
    "em_dash_interruption": 92.0,
    "em_dash_apposition": 17.0,
    "em_dash_amplification": 0.0,
    "em_dash_parenthetical": 172.0,
    "em_dash_glue": 584.0,
    "ellipsis_glyph_per_1k": 0.0,
    "ellipsis_triple_per_1k": 0.025190820465022547,
    "semicolon_per_1k": 13.267165444911873,
    "colon_per_1k": 0.6549613320905862,
    "parentheses_per_1k": 0.520610289610466,
    "bracket_per_1k": 0.0,
    "exclamation_per_1k": 4.693889546649201,
    "question_per_1k": 3.803813890218404,
    "interrobang_per_1k": 0.0,
    "caps_word_ratio": 0.0009740450579808717,
    "dialogue_line_ratio": 0.09828126483714747,
    "dialogue_line_count": 1035.0,
    "dash_led_dialogue_ratio": 0.0,
    "avg_words_between_dialogue": 113.38357487922706,
    "speaker_tag_rate_per_1k": 5.138927374864599,
    "hedge_per_1k": 2.460303465417202,
    "booster_per_1k": 9.4969393153135,
    "modal_per_1k": 17.81830700892595,
    "modal_must_ratio": 0.13336475023562677,
    "modal_should_ratio": 0.1112158341187559,
    "modal_can_ratio": 0.13996229971724788,
    "modal_could_ratio": 0.2714420358152686,
    "modal_might_ratio": 0.10131950989632423,
    "modal_would_ratio": 0.24269557021677662,
    "not_x_but_y_per_1k": 0.8732817761207816,
    "simile_like_per_1k": 0.03358776062003006,
    "simile_as_if_per_1k": 0.20992350387518788,
    "polysyndeton_and_per_1k": 28.818298611985792,
    "discourse_marker_per_sent": 0.008180839612486545,
    "sentence_mean_length": 25.63939720129171,
    "sentence_median_length": 20,
    "sentence_std_dev": 20.725106277342455,
    "sentence_long_share": 0.2008611410118407,
    "sentence_p90_length": 53.0,
    "sentence_length_entropy": 3.7165482888650665,
    "paragraph_length_entropy": 0.0,
    "paragraph_mean_length": 11.308612667363024,
    "paragraph_std_dev": 3.1505902100468073,
    "paragraph_cv": 0.278600948031362,
    "sentences_per_para_mean": 1.2963631184123066,
    "sentences_per_para_std": 0.5204078212254966,
    "sentences_per_para_cv": 0.40143676862919014,
    "sentences_per_para_entropy": 0.9740850258070546,
    "cconj_per_1k": 40.23813722279601,
    "sconj_per_1k": 30.15341209663199,
    "advcl_per_1k": 23.62059265603614,
    "ccomp_per_1k": 30.833564249187596,
    "mark_per_1k": 22.403036333560053,
    "verbless_sentence_ratio": 0.03789020452099031,
    "participial_opening_ratio": 0.004305705059203444,
    "fragment_ratio": 0.09967707212055975,
    "short_sentence_ratio": 0.14983853606027986,
    "parenthetical_per_1k": 3.88778329176848,
    "ttr": 0.052757974993912216,
    "hapax_ratio": 0.020379373756203238,
    "propn_ratio": 0.04903813050524389,
    "diacritic_ratio": 6.717552124006013e-05,
    "caps_word_count": 116.0,
    "noun_per_100": 14.636706384193598,
    "verb_per_100": 12.523196547178209,
    "adj_per_100": 6.655414766858956,
    "adv_per_100": 6.877933680966655,
    "pron_per_100": 15.693041455693546,
    "sight_per_100": 0.8497703436867605,
    "sound_per_100": 1.3376325666926971,
    "smell_per_100": 0.04954194691454434,
    "taste_per_100": 0.07641215541056838,
    "touch_per_100": 0.4803049768664299,
    "sensory_density_per_100": 2.7936619895710004,
    "sensory_dominant": "sound",
    "sensory_dominant_pct": 47.8809738503156,
    "sensory_entropy": 0.7377052084981214,
    "footnote_marker_per_1k": 0.0,
    "italics_token_count": 0.0,
    "smallcaps_token_count": 0.0,
    "translator_flag": 0.0,
    "edition_year": 0.0
  }
}