{
  "document": {
    "filename": "a-room-with-a-view-e-m-forster-1908-8aaf626b.txt",
    "source": "Project Gutenberg eBook #2641 (https://www.gutenberg.org/ebooks/2641)",
    "type": "unknown",
    "date": "unknown",
    "word_count": 66420,
    "metadata": {
      "title": "A Room with a View",
      "author": "E. M. Forster",
      "creator": "Forster, E. M.",
      "language": "en",
      "year": "1908",
      "published": "1908",
      "source": "Project Gutenberg eBook #2641 (https://www.gutenberg.org/ebooks/2641)",
      "rights": "Public domain in the USA (first published 1908)",
      "paragraphs": "2161",
      "word_count": "66420",
      "output_hash": "8aaf626b"
    },
    "form": "novel",
    "translation_status": "original_english",
    "translator": null,
    "fidelity_verdict": "clean",
    "centroid_membership": {
      "fiction_centroid": true,
      "translator_envelope": false,
      "control_shelf_calibration": true
    },
    "manifest_source_hash": "8aaf626b",
    "release_eligible_for_aggregates": true,
    "release_eligible_for_quotation": true
  },
  "pipeline": {
    "version": "v1.0",
    "schema_version": "1.0.0",
    "timestamp": "2026-06-10T10:43:23.716826",
    "components": [
      "D18++",
      "ai_detection_patterns",
      "emotion_analysis",
      "style_features"
    ]
  },
  "d18_profile": {
    "lexical_density": 0.47762615515111834,
    "content_words": 32096,
    "function_words": 35103,
    "abstract_ratio": 0.4743935309973046,
    "abstract_words": 704,
    "concrete_words": 780,
    "abstract_per_100": 1.0476346374201997,
    "concrete_per_100": 1.160731558505335,
    "formality_index": 0.0787914877613063,
    "latinate_count": 2514,
    "germanic_count": 29393,
    "latinate_per_100": 3.741127100105656,
    "germanic_per_100": 43.74023422967604,
    "complexity_score": 0.4058492032646716,
    "subordinate_clauses": 889,
    "coordinate_clauses": 2399,
    "avg_clause_length": 13.058492032646717,
    "mean_paragraph_length": 30.73577047663119,
    "stdev_paragraph_length": 36.777749191887324,
    "paragraph_cv": 1.196578078947132,
    "dominant_field": "social",
    "field_distribution": {
      "social": 0.2791111111111111,
      "perception": 0.14533333333333334,
      "cognition": 0.24755555555555556,
      "action": 0.08622222222222223,
      "communication": 0.16177777777777777,
      "emotion": 0.08
    },
    "sentiment_score": 0.0491708832807571,
    "repetition_ratio": 0.9498950877245197,
    "repeated_words": 63832,
    "unique_repeated": 3331,
    "metaphor_per_100": 0.8303694995461242,
    "metaphor_count": 558,
    "past_ratio": 0.5469387755102041,
    "present_ratio": 0.39645075421472936,
    "future_ratio": 0.05661047027506655,
    "dominant_tense": "past",
    "word_count": 67199,
    "sentence_count": 5146,
    "paragraph_count": 2161,
    "char_ngram_mean": 0.0414508215159429,
    "char_ngram_std": 0.015328222194809348,
    "char_ngram_nonzero": 512,
    "function_word_ratio_extended": 0.27997440438101756,
    "pronoun_first_sing_ratio": 0.20173893902707463,
    "pronoun_first_plur_ratio": 0.04611490204710544,
    "pronoun_second_ratio": 0.12392692053709004,
    "pronoun_third_ratio": 0.62821923838873,
    "dominant_perspective": "third_person",
    "self_focus_ratio": 0.24785384107418007,
    "sentence_mean_length": 13.058686358336573,
    "sentence_median_length": 11.0,
    "sentence_std_dev": 9.362421233237587,
    "sentence_cv": 0.7169496974142949,
    "hedge_count": 286,
    "epistemic_count": 242,
    "hedge_per_100": 0.42560157145195615,
    "epistemic_per_100": 0.3601244066131936,
    "certainty_index": -0.08333333333333333,
    "ttr": 0.09967410229318889,
    "unique_types": 6698,
    "hapax_legomena": 3367,
    "vocabulary_richness": 0.14977901456866918,
    "top_bigrams": [
      "buoni uomini",
      "contessa baroncelli",
      "dee sire",
      "inglese italianato",
      "partie carr\u00e9e",
      "sepulchral slabs",
      "andate via",
      "cinque lire",
      "decayed gentlewomen",
      "della robbia",
      "dozen yards",
      "military cloak",
      "orange cactus",
      "rev cuthbert",
      "semi detached"
    ],
    "top_trigrams": [
      "dee sire rebel",
      "della robbia babies",
      "joseph emery prank",
      "faremo uno giro",
      "signorino domani faremo",
      "domani faremo uno",
      "torre del gallo"
    ],
    "exclamation_per_1k": 6.741171743627137,
    "question_per_1k": 8.928704296194883,
    "em_dash_per_1k": 10.80373219839581,
    "ellipsis_per_1k": 0.07440586913495736,
    "semicolon_per_1k": 5.892944835488623
  },
  "ai_detection": {
    "not_x_but_y_score": 0,
    "em_dash_score": 59.30442637759712,
    "uniformity_score": 0,
    "beat_inconsistency_score": 100,
    "not_x_but_y_count": 0,
    "not_x_but_y_rate": 0.0,
    "em_dash_count": 726,
    "em_dash_rate": 10.930442637759711,
    "sentence_opening_entropy": 10.887430812694031,
    "paragraph_variance_cv": 0.6895114415831006,
    "word_count": 66420
  },
  "emotion": {
    "vader": {
      "compound": 0.0491708832807571,
      "positive": 0.09288848580441647,
      "negative": 0.07188706624605677,
      "neutral": 0.8352219242902199,
      "compound_mean": 0.0491708832807571,
      "compound_median": 0.0,
      "compound_std": 0.3390077413307624,
      "compound_min": -0.9532,
      "compound_max": 0.9686,
      "compound_q25": 0.0,
      "compound_q75": 0.25,
      "word_count": 66420,
      "sentence_count": 6340
    },
    "goemotions": null
  },
  "style_features": {
    "token_count": 67199,
    "sentence_count": 5146,
    "paragraph_count": 6418,
    "unique_types": 6698.0,
    "hapax_legomena": 3367.0,
    "avg_word_length": 4.238753552880251,
    "em_dash_per_1k": 10.80373219839581,
    "en_dash_per_1k": 0.0,
    "double_hyphen_per_1k": 0.0,
    "em_dash_total": 726.0,
    "em_dash_combined_per_1k": 10.80373219839581,
    "em_dash_reducible_count": 695.0,
    "em_dash_reducible_pct": 95.73002754820936,
    "em_dash_interruption": 31.0,
    "em_dash_apposition": 12.0,
    "em_dash_amplification": 0.0,
    "em_dash_parenthetical": 198.0,
    "em_dash_glue": 485.0,
    "ellipsis_glyph_per_1k": 0.0,
    "ellipsis_triple_per_1k": 0.07440586913495736,
    "semicolon_per_1k": 5.892944835488623,
    "colon_per_1k": 2.976234765398295,
    "parentheses_per_1k": 0.35714817184779535,
    "bracket_per_1k": 0.0,
    "exclamation_per_1k": 6.741171743627137,
    "question_per_1k": 8.928704296194883,
    "interrobang_per_1k": 0.0,
    "caps_word_ratio": 0.00043155404098275274,
    "dialogue_line_ratio": 0.23013399813025864,
    "dialogue_line_count": 1477.0,
    "dash_led_dialogue_ratio": 0.0,
    "avg_words_between_dialogue": 45.46174678402166,
    "speaker_tag_rate_per_1k": 9.017991339156833,
    "hedge_per_1k": 2.4107501599726184,
    "booster_per_1k": 5.163767317966041,
    "modal_per_1k": 13.259125879849401,
    "modal_must_ratio": 0.16161616161616163,
    "modal_should_ratio": 0.1324354657687991,
    "modal_can_ratio": 0.13131313131313133,
    "modal_could_ratio": 0.15824915824915825,
    "modal_might_ratio": 0.0931537598204265,
    "modal_would_ratio": 0.32323232323232326,
    "not_x_but_y_per_1k": 0.7589398651765651,
    "simile_like_per_1k": 0.4613163886367357,
    "simile_as_if_per_1k": 0.6250093007336419,
    "polysyndeton_and_per_1k": 27.26231045104838,
    "discourse_marker_per_sent": 0.01535172949863972,
    "sentence_mean_length": 13.058686358336573,
    "sentence_median_length": 11.0,
    "sentence_std_dev": 9.362421233237585,
    "sentence_long_share": 0.017683637776914108,
    "sentence_p90_length": 26.0,
    "sentence_length_entropy": 2.7036168879807505,
    "paragraph_length_entropy": 0.0,
    "paragraph_mean_length": 10.470395761919601,
    "paragraph_std_dev": 3.876981699462734,
    "paragraph_cv": 0.37028033969481433,
    "sentences_per_para_mean": 1.5377064506076659,
    "sentences_per_para_std": 0.6940264011699196,
    "sentences_per_para_cv": 0.45133868099184765,
    "sentences_per_para_entropy": 1.362110884630589,
    "cconj_per_1k": 38.46783434277295,
    "sconj_per_1k": 28.780190181401508,
    "advcl_per_1k": 19.553862408666795,
    "ccomp_per_1k": 37.753537999077366,
    "mark_per_1k": 19.449694191877853,
    "verbless_sentence_ratio": 0.05305091333074233,
    "participial_opening_ratio": 0.008161678973960357,
    "fragment_ratio": 0.1916051301982122,
    "short_sentence_ratio": 0.33618344345122425,
    "parenthetical_per_1k": 5.565559011294811,
    "ttr": 0.09967410229318889,
    "hapax_ratio": 0.05010491227548029,
    "propn_ratio": 0.07014985342043781,
    "diacritic_ratio": 0.00019345525975088916,
    "caps_word_count": 29.0,
    "noun_per_100": 14.251700174109732,
    "verb_per_100": 15.122248842988734,
    "adj_per_100": 6.285807824521199,
    "adv_per_100": 6.2411643030402235,
    "pron_per_100": 15.963035164213753,
    "sight_per_100": 1.1964463756901145,
    "sound_per_100": 2.003005997113052,
    "smell_per_100": 0.11458503846783433,
    "taste_per_100": 0.11458503846783433,
    "touch_per_100": 0.8645961993482045,
    "sensory_density_per_100": 4.29321864908704,
    "sensory_dominant": "sound",
    "sensory_dominant_pct": 46.65511265164645,
    "sensory_entropy": 0.7629420033828193,
    "footnote_marker_per_1k": 0.0,
    "italics_token_count": 0.0,
    "smallcaps_token_count": 0.0,
    "translator_flag": 0.0,
    "edition_year": 1908.0
  }
}