{
  "document": {
    "filename": "estate_sale__exemplar_morrison-toni__s1.txt",
    "source": "unknown",
    "type": "unknown",
    "date": "unknown",
    "word_count": 2137,
    "metadata": {}
  },
  "pipeline": {
    "version": "v1.0",
    "schema_version": "1.0.0",
    "timestamp": "2026-06-10T19:31:48.927353",
    "components": [
      "D18++",
      "ai_detection_patterns",
      "emotion_analysis",
      "style_features"
    ]
  },
  "d18_profile": {
    "lexical_density": 0.5004651162790698,
    "content_words": 1076,
    "function_words": 1074,
    "abstract_ratio": 0.21875,
    "abstract_words": 21,
    "concrete_words": 75,
    "abstract_per_100": 0.9767441860465116,
    "concrete_per_100": 3.488372093023256,
    "formality_index": 0.07845303867403315,
    "latinate_count": 71,
    "germanic_count": 834,
    "latinate_per_100": 3.302325581395349,
    "germanic_per_100": 38.79069767441861,
    "complexity_score": 0.3431372549019608,
    "subordinate_clauses": 26,
    "coordinate_clauses": 53,
    "avg_clause_length": 14.052287581699346,
    "mean_paragraph_length": 40.320754716981135,
    "stdev_paragraph_length": 23.970152581993798,
    "paragraph_cv": 0.5944867041860885,
    "dominant_field": "social",
    "field_distribution": {
      "social": 0.5362318840579711,
      "perception": 0.2463768115942029,
      "action": 0.057971014492753624,
      "cognition": 0.08695652173913043,
      "communication": 0.057971014492753624,
      "emotion": 0.014492753623188406
    },
    "sentiment_score": -0.03690063694267516,
    "repetition_ratio": 0.7753488372093024,
    "repeated_words": 1667,
    "unique_repeated": 236,
    "metaphor_per_100": 0.9767441860465116,
    "metaphor_count": 21,
    "past_ratio": 0.8597560975609756,
    "present_ratio": 0.1402439024390244,
    "future_ratio": 0.0,
    "dominant_tense": "past",
    "word_count": 2150,
    "sentence_count": 153,
    "paragraph_count": 53,
    "char_ngram_mean": 0.03808233099926546,
    "char_ngram_std": 0.022424563890126932,
    "char_ngram_nonzero": 512,
    "function_word_ratio_extended": 0.36093023255813955,
    "pronoun_first_sing_ratio": 0.011363636363636364,
    "pronoun_first_plur_ratio": 0.005681818181818182,
    "pronoun_second_ratio": 0.03409090909090909,
    "pronoun_third_ratio": 0.9488636363636364,
    "dominant_perspective": "third_person",
    "self_focus_ratio": 0.017045454545454544,
    "sentence_mean_length": 14.052287581699346,
    "sentence_median_length": 13.0,
    "sentence_std_dev": 8.523547429330225,
    "sentence_cv": 0.6065594217151277,
    "hedge_count": 5,
    "epistemic_count": 0,
    "hedge_per_100": 0.23255813953488372,
    "epistemic_per_100": 0.0,
    "certainty_index": -1.0,
    "ttr": 0.3344186046511628,
    "unique_types": 719,
    "hapax_legomena": 483,
    "vocabulary_richness": 0.5590697674418604,
    "top_bigrams": [
      "gravel driveway",
      "i got",
      "leathered skin",
      "long time",
      "nothing left",
      "tea cup",
      "no longer",
      "hollowed out",
      "you keep",
      "out spaces",
      "empty rooms",
      "pressed against",
      "those hands",
      "dining room",
      "younger man"
    ],
    "top_trigrams": [
      "hollowed out spaces",
      "i got it",
      "seemed to settle",
      "dining room through",
      "was no longer",
      "a long time",
      "looked back into"
    ],
    "exclamation_per_1k": 0.930232558139535,
    "question_per_1k": 2.7906976744186047,
    "em_dash_per_1k": 1.86046511627907,
    "ellipsis_per_1k": 0.0,
    "semicolon_per_1k": 0.930232558139535
  },
  "ai_detection": {
    "not_x_but_y_score": 0,
    "em_dash_score": 0,
    "uniformity_score": 0,
    "beat_inconsistency_score": 100,
    "not_x_but_y_count": 0,
    "not_x_but_y_rate": 0.0,
    "em_dash_count": 4,
    "em_dash_rate": 1.8717828731867105,
    "sentence_opening_entropy": 6.761025605510622,
    "paragraph_variance_cv": 0.5215026672666413,
    "word_count": 2137
  },
  "emotion": {
    "vader": {
      "compound": -0.03690063694267516,
      "positive": 0.04469426751592356,
      "negative": 0.05963694267515921,
      "neutral": 0.895656050955414,
      "compound_mean": -0.03690063694267516,
      "compound_median": 0.0,
      "compound_std": 0.2865331586722601,
      "compound_min": -0.7506,
      "compound_max": 0.8402,
      "compound_q25": -0.2023,
      "compound_q75": 0.0,
      "word_count": 2137,
      "sentence_count": 157
    },
    "goemotions": null
  },
  "style_features": {
    "token_count": 2150,
    "sentence_count": 153,
    "paragraph_count": 53,
    "unique_types": 719.0,
    "hapax_legomena": 483.0,
    "avg_word_length": 4.402325581395349,
    "em_dash_per_1k": 1.86046511627907,
    "en_dash_per_1k": 0.0,
    "double_hyphen_per_1k": 0.0,
    "em_dash_total": 4.0,
    "em_dash_combined_per_1k": 1.86046511627907,
    "em_dash_reducible_count": 4.0,
    "em_dash_reducible_pct": 100.0,
    "em_dash_interruption": 0.0,
    "em_dash_apposition": 1.0,
    "em_dash_amplification": 0.0,
    "em_dash_parenthetical": 0.0,
    "em_dash_glue": 3.0,
    "ellipsis_glyph_per_1k": 0.0,
    "ellipsis_triple_per_1k": 0.0,
    "semicolon_per_1k": 0.930232558139535,
    "colon_per_1k": 0.4651162790697675,
    "parentheses_per_1k": 0.0,
    "bracket_per_1k": 0.0,
    "exclamation_per_1k": 0.930232558139535,
    "question_per_1k": 2.7906976744186047,
    "interrobang_per_1k": 0.0,
    "caps_word_ratio": 0.0,
    "dialogue_line_ratio": 0.22641509433962265,
    "dialogue_line_count": 12.0,
    "dash_led_dialogue_ratio": 0.0,
    "avg_words_between_dialogue": 165.33333333333334,
    "speaker_tag_rate_per_1k": 6.046511627906977,
    "hedge_per_1k": 1.86046511627907,
    "booster_per_1k": 5.116279069767441,
    "modal_per_1k": 2.7906976744186047,
    "modal_must_ratio": 0.0,
    "modal_should_ratio": 0.0,
    "modal_can_ratio": 0.0,
    "modal_could_ratio": 0.8333333333333334,
    "modal_might_ratio": 0.0,
    "modal_would_ratio": 0.16666666666666666,
    "not_x_but_y_per_1k": 0.930232558139535,
    "simile_like_per_1k": 1.86046511627907,
    "simile_as_if_per_1k": 0.930232558139535,
    "polysyndeton_and_per_1k": 17.674418604651162,
    "discourse_marker_per_sent": 0.0,
    "sentence_mean_length": 14.052287581699346,
    "sentence_median_length": 13,
    "sentence_std_dev": 8.523547429330224,
    "sentence_long_share": 0.013071895424836602,
    "sentence_p90_length": 25.0,
    "sentence_length_entropy": 2.695895722084508,
    "paragraph_length_entropy": 2.226465799646592,
    "paragraph_mean_length": 40.56603773584906,
    "paragraph_std_dev": 23.968933851150748,
    "paragraph_cv": 0.5908620902841812,
    "sentences_per_para_mean": 2.981132075471698,
    "sentences_per_para_std": 1.3386922094390008,
    "sentences_per_para_cv": 0.4490549816472598,
    "sentences_per_para_entropy": 2.3677826736293914,
    "cconj_per_1k": 21.86046511627907,
    "sconj_per_1k": 12.558139534883722,
    "advcl_per_1k": 20.0,
    "ccomp_per_1k": 11.627906976744185,
    "mark_per_1k": 6.046511627906977,
    "verbless_sentence_ratio": 0.032679738562091505,
    "participial_opening_ratio": 0.0,
    "fragment_ratio": 0.1437908496732026,
    "short_sentence_ratio": 0.2679738562091503,
    "parenthetical_per_1k": 0.930232558139535,
    "ttr": 0.3344186046511628,
    "hapax_ratio": 0.22465116279069766,
    "propn_ratio": 0.013953488372093023,
    "diacritic_ratio": 0.0,
    "caps_word_count": 0.0,
    "noun_per_100": 23.627906976744185,
    "verb_per_100": 13.627906976744185,
    "adj_per_100": 8.093023255813954,
    "adv_per_100": 3.2093023255813953,
    "pron_per_100": 10.55813953488372,
    "sight_per_100": 2.697674418604651,
    "sound_per_100": 2.372093023255814,
    "smell_per_100": 0.37209302325581395,
    "taste_per_100": 0.0,
    "touch_per_100": 4.4186046511627906,
    "sensory_density_per_100": 9.86046511627907,
    "sensory_dominant": "touch",
    "sensory_dominant_pct": 44.81132075471698,
    "sensory_entropy": 0.7336255479187509,
    "footnote_marker_per_1k": 0.0,
    "italics_token_count": 0.0,
    "smallcaps_token_count": 0.0,
    "translator_flag": 0.0,
    "edition_year": 0.0
  }
}