{
  "document": {
    "filename": "hotel_fire__unprompted.txt",
    "source": "unknown",
    "type": "unknown",
    "date": "unknown",
    "word_count": 2690,
    "metadata": {}
  },
  "pipeline": {
    "version": "v1.0",
    "schema_version": "1.0.0",
    "timestamp": "2026-06-09T19:02:13.739534",
    "components": [
      "D18++",
      "ai_detection_patterns",
      "emotion_analysis",
      "style_features"
    ]
  },
  "d18_profile": {
    "lexical_density": 0.5095870206489675,
    "content_words": 1382,
    "function_words": 1330,
    "abstract_ratio": 0.22,
    "abstract_words": 22,
    "concrete_words": 78,
    "abstract_per_100": 0.8112094395280236,
    "concrete_per_100": 2.8761061946902653,
    "formality_index": 0.1383399209486166,
    "latinate_count": 175,
    "germanic_count": 1090,
    "latinate_per_100": 6.452802359882005,
    "germanic_per_100": 40.19174041297935,
    "complexity_score": 0.35082872928176795,
    "subordinate_clauses": 32,
    "coordinate_clauses": 63,
    "avg_clause_length": 14.98342541436464,
    "mean_paragraph_length": 51.73076923076923,
    "stdev_paragraph_length": 26.57738636629547,
    "paragraph_cv": 0.5137636026198381,
    "dominant_field": "perception",
    "field_distribution": {
      "action": 0.16,
      "social": 0.34,
      "perception": 0.36,
      "cognition": 0.12,
      "emotion": 0.02
    },
    "sentiment_score": 0.0753726775956284,
    "repetition_ratio": 0.7765486725663717,
    "repeated_words": 2106,
    "unique_repeated": 306,
    "metaphor_per_100": 1.2905604719764012,
    "metaphor_count": 35,
    "past_ratio": 0.890625,
    "present_ratio": 0.10416666666666667,
    "future_ratio": 0.005208333333333333,
    "dominant_tense": "past",
    "word_count": 2712,
    "sentence_count": 181,
    "paragraph_count": 52,
    "char_ngram_mean": 0.03859790505417055,
    "char_ngram_std": 0.021525025561639533,
    "char_ngram_nonzero": 512,
    "function_word_ratio_extended": 0.35693215339233036,
    "pronoun_first_sing_ratio": 0.013513513513513514,
    "pronoun_first_plur_ratio": 0.0045045045045045045,
    "pronoun_second_ratio": 0.04954954954954955,
    "pronoun_third_ratio": 0.9324324324324325,
    "dominant_perspective": "third_person",
    "self_focus_ratio": 0.018018018018018018,
    "sentence_mean_length": 14.98342541436464,
    "sentence_median_length": 14.0,
    "sentence_std_dev": 8.625719691726488,
    "sentence_cv": 0.5756840944699463,
    "hedge_count": 8,
    "epistemic_count": 3,
    "hedge_per_100": 0.2949852507374631,
    "epistemic_per_100": 0.11061946902654868,
    "certainty_index": -0.45454545454545453,
    "ttr": 0.336283185840708,
    "unique_types": 912,
    "hapax_legomena": 606,
    "vocabulary_richness": 0.5597345132743363,
    "top_bigrams": [
      "climate control",
      "i suppose",
      "sapphire suite",
      "thought about",
      "never truly",
      "revolving doors",
      "reception desk",
      "would remain",
      "someone who",
      "did need",
      "no amount",
      "replaced by",
      "service corridors",
      "young man",
      "exist without"
    ],
    "top_trigrams": [
      "not exist without",
      "could not exist",
      "seemed to vanish",
      "cool and smelled",
      "she thought about",
      "that no amount",
      "someone who had"
    ],
    "exclamation_per_1k": 0.0,
    "question_per_1k": 1.4749262536873156,
    "em_dash_per_1k": 5.899705014749262,
    "ellipsis_per_1k": 0.7374631268436578,
    "semicolon_per_1k": 0.3687315634218289
  },
  "ai_detection": {
    "not_x_but_y_score": 0,
    "em_dash_score": 9.479553903345717,
    "uniformity_score": 0,
    "beat_inconsistency_score": 55.921975168888196,
    "not_x_but_y_count": 0,
    "not_x_but_y_rate": 0.0,
    "em_dash_count": 16,
    "em_dash_rate": 5.947955390334572,
    "sentence_opening_entropy": 6.68701819625265,
    "paragraph_variance_cv": 0.4118439503377764,
    "word_count": 2690
  },
  "emotion": {
    "vader": {
      "compound": 0.0753726775956284,
      "positive": 0.08433879781420767,
      "negative": 0.04194535519125683,
      "neutral": 0.8737322404371586,
      "compound_mean": 0.0753726775956284,
      "compound_median": 0.0,
      "compound_std": 0.3092734998725749,
      "compound_min": -0.5719,
      "compound_max": 0.9169,
      "compound_q25": 0.0,
      "compound_q75": 0.3182,
      "word_count": 2690,
      "sentence_count": 183
    },
    "goemotions": null
  },
  "style_features": {
    "token_count": 2712,
    "sentence_count": 181,
    "paragraph_count": 52,
    "unique_types": 912.0,
    "hapax_legomena": 606.0,
    "avg_word_length": 4.536873156342183,
    "em_dash_per_1k": 5.899705014749262,
    "en_dash_per_1k": 0.0,
    "double_hyphen_per_1k": 0.0,
    "em_dash_total": 16.0,
    "em_dash_combined_per_1k": 5.899705014749262,
    "em_dash_reducible_count": 15.0,
    "em_dash_reducible_pct": 93.75,
    "em_dash_interruption": 1.0,
    "em_dash_apposition": 0.0,
    "em_dash_amplification": 0.0,
    "em_dash_parenthetical": 0.0,
    "em_dash_glue": 15.0,
    "ellipsis_glyph_per_1k": 0.7374631268436578,
    "ellipsis_triple_per_1k": 0.0,
    "semicolon_per_1k": 0.3687315634218289,
    "colon_per_1k": 0.0,
    "parentheses_per_1k": 0.0,
    "bracket_per_1k": 0.0,
    "exclamation_per_1k": 0.0,
    "question_per_1k": 1.4749262536873156,
    "interrobang_per_1k": 0.0,
    "caps_word_ratio": 0.0,
    "dialogue_line_ratio": 0.17307692307692307,
    "dialogue_line_count": 9.0,
    "dash_led_dialogue_ratio": 0.0,
    "avg_words_between_dialogue": 191.33333333333334,
    "speaker_tag_rate_per_1k": 2.2123893805309733,
    "hedge_per_1k": 2.5811209439528024,
    "booster_per_1k": 2.5811209439528024,
    "modal_per_1k": 5.899705014749262,
    "modal_must_ratio": 0.0,
    "modal_should_ratio": 0.0,
    "modal_can_ratio": 0.125,
    "modal_could_ratio": 0.6875,
    "modal_might_ratio": 0.0,
    "modal_would_ratio": 0.1875,
    "not_x_but_y_per_1k": 0.7374631268436578,
    "simile_like_per_1k": 2.2123893805309733,
    "simile_as_if_per_1k": 1.8436578171091444,
    "polysyndeton_and_per_1k": 15.117994100294984,
    "discourse_marker_per_sent": 0.0,
    "sentence_mean_length": 14.98342541436464,
    "sentence_median_length": 14,
    "sentence_std_dev": 8.625719691726488,
    "sentence_long_share": 0.0055248618784530384,
    "sentence_p90_length": 27.0,
    "sentence_length_entropy": 2.7492473417209657,
    "paragraph_length_entropy": 2.4193507296320034,
    "paragraph_mean_length": 52.15384615384615,
    "paragraph_std_dev": 26.45851950578244,
    "paragraph_cv": 0.507316745686094,
    "sentences_per_para_mean": 3.519230769230769,
    "sentences_per_para_std": 1.2783761426630964,
    "sentences_per_para_cv": 0.36325442305180883,
    "sentences_per_para_entropy": 2.349328790556039,
    "cconj_per_1k": 19.1740412979351,
    "sconj_per_1k": 19.542772861356934,
    "advcl_per_1k": 21.755162241887906,
    "ccomp_per_1k": 13.274336283185841,
    "mark_per_1k": 15.486725663716815,
    "verbless_sentence_ratio": 0.03314917127071823,
    "participial_opening_ratio": 0.0,
    "fragment_ratio": 0.13812154696132597,
    "short_sentence_ratio": 0.2265193370165746,
    "parenthetical_per_1k": 2.949852507374631,
    "ttr": 0.336283185840708,
    "hapax_ratio": 0.2234513274336283,
    "propn_ratio": 0.01733038348082596,
    "diacritic_ratio": 0.0,
    "caps_word_count": 0.0,
    "noun_per_100": 22.087020648967552,
    "verb_per_100": 13.274336283185843,
    "adj_per_100": 9.402654867256636,
    "adv_per_100": 4.572271386430678,
    "pron_per_100": 10.58259587020649,
    "sight_per_100": 2.949852507374631,
    "sound_per_100": 1.4380530973451326,
    "smell_per_100": 0.7005899705014749,
    "taste_per_100": 0.18436578171091444,
    "touch_per_100": 3.7241887905604716,
    "sensory_density_per_100": 8.997050147492626,
    "sensory_dominant": "touch",
    "sensory_dominant_pct": 41.39344262295082,
    "sensory_entropy": 0.8091342069922531,
    "footnote_marker_per_1k": 0.0,
    "italics_token_count": 0.0,
    "smallcaps_token_count": 0.0,
    "translator_flag": 0.0,
    "edition_year": 0.0
  }
}