{
  "document": {
    "filename": "irrigation__para_workshop__s1.txt",
    "source": "unknown",
    "type": "unknown",
    "date": "unknown",
    "word_count": 1625,
    "metadata": {}
  },
  "pipeline": {
    "version": "v1.0",
    "schema_version": "1.0.0",
    "timestamp": "2026-06-10T19:33:19.168472",
    "components": [
      "D18++",
      "ai_detection_patterns",
      "emotion_analysis",
      "style_features"
    ]
  },
  "d18_profile": {
    "lexical_density": 0.5061199510403916,
    "content_words": 827,
    "function_words": 807,
    "abstract_ratio": 0.27692307692307694,
    "abstract_words": 18,
    "concrete_words": 47,
    "abstract_per_100": 1.101591187270502,
    "concrete_per_100": 2.876376988984088,
    "formality_index": 0.08213820078226858,
    "latinate_count": 63,
    "germanic_count": 704,
    "latinate_per_100": 3.8555691554467564,
    "germanic_per_100": 43.08445532435741,
    "complexity_score": 0.28888888888888886,
    "subordinate_clauses": 22,
    "coordinate_clauses": 34,
    "avg_clause_length": 12.103703703703705,
    "mean_paragraph_length": 54.166666666666664,
    "stdev_paragraph_length": 27.549433104291204,
    "paragraph_cv": 0.508604918848453,
    "dominant_field": "action",
    "field_distribution": {
      "perception": 0.2,
      "social": 0.16666666666666666,
      "cognition": 0.2,
      "action": 0.26666666666666666,
      "emotion": 0.06666666666666667,
      "communication": 0.1
    },
    "sentiment_score": -0.05695886524822695,
    "repetition_ratio": 0.762545899632803,
    "repeated_words": 1246,
    "unique_repeated": 208,
    "metaphor_per_100": 0.4895960832313341,
    "metaphor_count": 8,
    "past_ratio": 0.7448979591836735,
    "present_ratio": 0.25510204081632654,
    "future_ratio": 0.0,
    "dominant_tense": "past",
    "word_count": 1634,
    "sentence_count": 135,
    "paragraph_count": 30,
    "char_ngram_mean": 0.03845413103591679,
    "char_ngram_std": 0.021780835756980057,
    "char_ngram_nonzero": 512,
    "function_word_ratio_extended": 0.3408812729498164,
    "pronoun_first_sing_ratio": 0.050955414012738856,
    "pronoun_first_plur_ratio": 0.09554140127388536,
    "pronoun_second_ratio": 0.14012738853503184,
    "pronoun_third_ratio": 0.7133757961783439,
    "dominant_perspective": "third_person",
    "self_focus_ratio": 0.1464968152866242,
    "sentence_mean_length": 12.103703703703705,
    "sentence_median_length": 10.0,
    "sentence_std_dev": 8.59825483936007,
    "sentence_cv": 0.7103821317708748,
    "hedge_count": 2,
    "epistemic_count": 0,
    "hedge_per_100": 0.12239902080783352,
    "epistemic_per_100": 0.0,
    "certainty_index": -1.0,
    "ttr": 0.36474908200734396,
    "unique_types": 596,
    "hapax_legomena": 388,
    "vocabulary_richness": 0.6022031823745411,
    "top_bigrams": [
      "north forty",
      "what happens",
      "house becomes",
      "left us",
      "talking about",
      "did say",
      "pump is",
      "every time",
      "looking at",
      "had been",
      "looked at",
      "that seemed",
      "i not",
      "looking for",
      "even if"
    ],
    "top_trigrams": [
      "seemed to be",
      "what happens to",
      "house becomes a",
      "i ca just",
      "left us a",
      "every time you",
      "he did say"
    ],
    "exclamation_per_1k": 0.0,
    "question_per_1k": 1.2239902080783354,
    "em_dash_per_1k": 2.4479804161566707,
    "ellipsis_per_1k": 0.6119951040391677,
    "semicolon_per_1k": 0.0
  },
  "ai_detection": {
    "not_x_but_y_score": 0,
    "em_dash_score": 0,
    "uniformity_score": 0,
    "beat_inconsistency_score": 100,
    "not_x_but_y_count": 0,
    "not_x_but_y_rate": 0.0,
    "em_dash_count": 4,
    "em_dash_rate": 2.4615384615384617,
    "sentence_opening_entropy": 6.516329345441849,
    "paragraph_variance_cv": 0.5120219462652632,
    "word_count": 1625
  },
  "emotion": {
    "vader": {
      "compound": -0.05695886524822695,
      "positive": 0.04053191489361702,
      "negative": 0.069354609929078,
      "neutral": 0.8901134751773053,
      "compound_mean": -0.05695886524822695,
      "compound_median": 0.0,
      "compound_std": 0.26851545251067066,
      "compound_min": -0.9001,
      "compound_max": 0.6369,
      "compound_q25": -0.0516,
      "compound_q75": 0.0,
      "word_count": 1625,
      "sentence_count": 141
    },
    "goemotions": null
  },
  "style_features": {
    "token_count": 1634,
    "sentence_count": 135,
    "paragraph_count": 30,
    "unique_types": 596.0,
    "hapax_legomena": 388.0,
    "avg_word_length": 4.19828641370869,
    "em_dash_per_1k": 2.4479804161566707,
    "en_dash_per_1k": 0.0,
    "double_hyphen_per_1k": 0.0,
    "em_dash_total": 4.0,
    "em_dash_combined_per_1k": 2.4479804161566707,
    "em_dash_reducible_count": 3.0,
    "em_dash_reducible_pct": 75.0,
    "em_dash_interruption": 1.0,
    "em_dash_apposition": 0.0,
    "em_dash_amplification": 0.0,
    "em_dash_parenthetical": 0.0,
    "em_dash_glue": 3.0,
    "ellipsis_glyph_per_1k": 0.0,
    "ellipsis_triple_per_1k": 0.6119951040391677,
    "semicolon_per_1k": 0.0,
    "colon_per_1k": 0.0,
    "parentheses_per_1k": 0.0,
    "bracket_per_1k": 0.0,
    "exclamation_per_1k": 0.0,
    "question_per_1k": 1.2239902080783354,
    "interrobang_per_1k": 0.0,
    "caps_word_ratio": 0.0006119951040391676,
    "dialogue_line_ratio": 0.5333333333333333,
    "dialogue_line_count": 16.0,
    "dash_led_dialogue_ratio": 0.0,
    "avg_words_between_dialogue": 97.125,
    "speaker_tag_rate_per_1k": 7.95593635250918,
    "hedge_per_1k": 1.2239902080783354,
    "booster_per_1k": 4.8959608323133414,
    "modal_per_1k": 6.119951040391677,
    "modal_must_ratio": 0.0,
    "modal_should_ratio": 0.0,
    "modal_can_ratio": 0.0,
    "modal_could_ratio": 0.4,
    "modal_might_ratio": 0.1,
    "modal_would_ratio": 0.5,
    "not_x_but_y_per_1k": 0.6119951040391677,
    "simile_like_per_1k": 1.2239902080783354,
    "simile_as_if_per_1k": 0.0,
    "polysyndeton_and_per_1k": 12.851897184822521,
    "discourse_marker_per_sent": 0.0,
    "sentence_mean_length": 12.103703703703705,
    "sentence_median_length": 10,
    "sentence_std_dev": 8.59825483936007,
    "sentence_long_share": 0.007407407407407408,
    "sentence_p90_length": 23.60000000000001,
    "sentence_length_entropy": 2.592066615502924,
    "paragraph_length_entropy": 2.3511894468399483,
    "paragraph_mean_length": 54.46666666666667,
    "paragraph_std_dev": 27.25036187323431,
    "paragraph_cv": 0.50031264149145,
    "sentences_per_para_mean": 4.7,
    "sentences_per_para_std": 2.3115651263447745,
    "sentences_per_para_cv": 0.4918223673073988,
    "sentences_per_para_entropy": 2.819250912838829,
    "cconj_per_1k": 17.135862913096695,
    "sconj_per_1k": 15.91187270501836,
    "advcl_per_1k": 25.091799265605875,
    "ccomp_per_1k": 23.867809057527538,
    "mark_per_1k": 12.851897184822521,
    "verbless_sentence_ratio": 0.0,
    "participial_opening_ratio": 0.007407407407407408,
    "fragment_ratio": 0.17037037037037037,
    "short_sentence_ratio": 0.3851851851851852,
    "parenthetical_per_1k": 1.2239902080783354,
    "ttr": 0.36474908200734396,
    "hapax_ratio": 0.23745410036719705,
    "propn_ratio": 0.02692778457772338,
    "diacritic_ratio": 0.0,
    "caps_word_count": 1.0,
    "noun_per_100": 22.52141982864137,
    "verb_per_100": 16.768665850673194,
    "adj_per_100": 5.691554467564259,
    "adv_per_100": 3.610771113831089,
    "pron_per_100": 11.383108935128519,
    "sight_per_100": 2.386780905752754,
    "sound_per_100": 1.9583843329253363,
    "smell_per_100": 0.42839657282741733,
    "taste_per_100": 0.42839657282741733,
    "touch_per_100": 2.7539779681762546,
    "sensory_density_per_100": 7.9559363525091795,
    "sensory_dominant": "touch",
    "sensory_dominant_pct": 34.61538461538461,
    "sensory_entropy": 0.8624820549507712,
    "footnote_marker_per_1k": 0.0,
    "italics_token_count": 0.0,
    "smallcaps_token_count": 0.0,
    "translator_flag": 0.0,
    "edition_year": 0.0
  }
}